odoo/addons/product_name_with_attributes/README.rst
odoo/addons/product_name_with_attributes/__init__.py
odoo/addons/product_name_with_attributes/__manifest__.py
odoo/addons/product_name_with_attributes/models/__init__.py
odoo/addons/product_name_with_attributes/models/product.py
odoo/addons/product_name_with_attributes/models/product_attribute.py
odoo/addons/product_name_with_attributes/static/description/icon.png
odoo/addons/product_name_with_attributes/views/sale_order_views.xml
odoo_addon_product_name_with_attributes-16.0.1.0.0.2.dist-info/METADATA
odoo_addon_product_name_with_attributes-16.0.1.0.0.2.dist-info/WHEEL
odoo_addon_product_name_with_attributes-16.0.1.0.0.2.dist-info/top_level.txt
odoo_addon_product_name_with_attributes-16.0.1.0.0.2.dist-info/RECORD
